{"cameraMode":{"drawMode":0,"name":"Shaded","section":"Shading Mode"},"sceneLighting":true,"audioPlay":false,"sceneViewState":{"m_AlwaysRefresh":false,"showFog":true,"showSkybox":true,"showFlares":true,"showImageEffects":true,"showParticleSystems":true,"showVisualEffectGraphs":true,"m_FxEnabled":false},"in2DMode":false,"pivot":{"x":41.35460662841797,"y":2.328533172607422,"z":3.722032070159912},"rotation":{"x":-0.002880039857700467,"y":-0.9949550628662109,"z":0.0958108976483345,"w":-0.02984761819243431},"size":1.0862778425216675,"orthographic":false}